{
    "Instruction": "Search your surroundings and navigate to the crate.",
    "Reason": "Requires exploration and visual search (Challenge 1), as the crate is not visible in the current view.",
    "Type": 1,
    "GenAI_Target_Object": [
        "Crate70_45"
    ],
    "Start_Pose": [
        719.221,
        -8341.369,
        2090.607,
        0.0,
        112.176,
        0.0
    ],
    "Action": [
        "TurnLeft",
        "TurnLeft",
        "MoveForward",
        "MoveForward",
        "MoveForward",
        "TurnLeft",
        "Finish"
    ],
    "Target_Pose": [
        [
            1150.078,
            -7828.597,
            1978.275,
            0.0,
            19.578,
            0.0
        ]
    ],
    "Trajectory_Pose": [
        [
            719.221,
            -8341.369,
            2090.607,
            0.0,
            112.176,
            0.0
        ],
        [
            719.221,
            -8341.369,
            2090.607,
            0.0,
            81.168,
            0.0
        ],
        [
            719.221,
            -8341.369,
            2090.607,
            0.0,
            49.961,
            0.0
        ],
        [
            852.497,
            -8182.762,
            1978.275,
            0.0,
            49.961,
            0.0
        ],
        [
            1003.087,
            -8003.539,
            1978.275,
            0.0,
            49.961,
            0.0
        ],
        [
            1150.078,
            -7828.597,
            1978.275,
            0.0,
            49.961,
            0.0
        ],
        [
            1150.078,
            -7828.597,
            1978.275,
            0.0,
            19.578,
            0.0
        ]
    ]
}